zabbix_cachet/__init__.py
zabbix_cachet/cachet.py
zabbix_cachet/excepltions.py
zabbix_cachet/main.py
zabbix_cachet/zabbix.py
zabbix_cachet-2.1.3.dist-info/LICENSE
zabbix_cachet-2.1.3.dist-info/METADATA
zabbix_cachet-2.1.3.dist-info/WHEEL
zabbix_cachet-2.1.3.dist-info/entry_points.txt
zabbix_cachet-2.1.3.dist-info/RECORD
