Metadata-Version: 2.1
Name: zabbix-cachet
Version: 2.1.3
Summary: Python daemon which provides synchronisation between Zabbix IT Services and Cachet
License: MIT
Author: Artem Alexandrov
Author-email: qk4l@tem4uk.ru
Requires-Python: >3.8,<4.0
Classifier: License :: OSI Approved :: MIT License
Classifier: Programming Language :: Python :: 3
Classifier: Programming Language :: Python :: 3.9
Classifier: Programming Language :: Python :: 3.10
Classifier: Programming Language :: Python :: 3.11
Classifier: Programming Language :: Python :: 3.12
Requires-Dist: pytz (>=2024.1)
Requires-Dist: pyyaml (>=5.4)
Requires-Dist: pyzabbix (==1.3.1)
Requires-Dist: requests (>2.21.0)
